{"_invocation_id": "7dedded1-821b-417a-8e05-4dd9e8b5b975", "linked": {"0": {"name": "source.my_dbt_project.raw.green_tripdata_2018-01", "type": "source"}, "1": {"name": "source.my_dbt_project.raw.green_tripdata_2018-02", "type": "source"}, "2": {"name": "source.my_dbt_project.raw.green_tripdata_2018-03", "type": "source"}, "3": {"name": "source.my_dbt_project.raw.green_tripdata_2018-04", "type": "source"}, "4": {"name": "source.my_dbt_project.raw.green_tripdata_2018-05", "type": "source"}, "5": {"name": "source.my_dbt_project.raw.green_tripdata_2018-06", "type": "source"}, "6": {"name": "source.my_dbt_project.raw.green_tripdata_2018-07", "type": "source"}, "7": {"name": "source.my_dbt_project.raw.green_tripdata_2018-08", "type": "source"}, "8": {"name": "source.my_dbt_project.raw.green_tripdata_2018-09", "type": "source"}, "9": {"name": "source.my_dbt_project.raw.green_tripdata_2018-10", "type": "source"}, "10": {"name": "source.my_dbt_project.raw.green_tripdata_2018-11", "type": "source"}, "11": {"name": "source.my_dbt_project.raw.green_tripdata_2018-12", "type": "source"}, "12": {"name": "source.my_dbt_project.raw.green_tripdata_2019-01", "type": "source"}, "13": {"name": "source.my_dbt_project.raw.green_tripdata_2019-02", "type": "source"}, "14": {"name": "source.my_dbt_project.raw.green_tripdata_2019-03", "type": "source"}, "15": {"name": "source.my_dbt_project.raw.green_tripdata_2019-04", "type": "source"}, "16": {"name": "source.my_dbt_project.raw.green_tripdata_2019-05", "type": "source"}, "17": {"name": "source.my_dbt_project.raw.green_tripdata_2019-06", "type": "source"}, "18": {"name": "source.my_dbt_project.raw.green_tripdata_2019-07", "type": "source"}, "19": {"name": "source.my_dbt_project.raw.green_tripdata_2019-08", "type": "source"}, "20": {"name": "source.my_dbt_project.raw.green_tripdata_2019-09", "type": "source"}, "21": {"name": "source.my_dbt_project.raw.green_tripdata_2019-10", "type": "source"}, "22": {"name": "source.my_dbt_project.raw.green_tripdata_2019-11", "type": "source"}, "23": {"name": "source.my_dbt_project.raw.green_tripdata_2019-12", "type": "source"}, "24": {"name": "source.my_dbt_project.raw.green_tripdata_2020-01", "type": "source"}, "25": {"name": "source.my_dbt_project.raw.green_tripdata_2020-02", "type": "source"}, "26": {"name": "source.my_dbt_project.raw.green_tripdata_2020-03", "type": "source"}, "27": {"name": "source.my_dbt_project.raw.green_tripdata_2020-04", "type": "source"}, "28": {"name": "source.my_dbt_project.raw.green_tripdata_2020-05", "type": "source"}, "29": {"name": "source.my_dbt_project.raw.green_tripdata_2020-06", "type": "source"}, "30": {"name": "source.my_dbt_project.raw.green_tripdata_2020-07", "type": "source"}, "31": {"name": "source.my_dbt_project.raw.green_tripdata_2020-08", "type": "source"}, "32": {"name": "source.my_dbt_project.raw.green_tripdata_2020-09", "type": "source"}, "33": {"name": "source.my_dbt_project.raw.green_tripdata_2020-10", "type": "source"}, "34": {"name": "source.my_dbt_project.raw.green_tripdata_2020-11", "type": "source"}, "35": {"name": "source.my_dbt_project.raw.green_tripdata_2020-12", "type": "source"}, "36": {"name": "source.my_dbt_project.raw.green_tripdata_2021-01", "type": "source"}, "37": {"name": "source.my_dbt_project.raw.green_tripdata_2021-02", "type": "source"}, "38": {"name": "source.my_dbt_project.raw.green_tripdata_2021-03", "type": "source"}, "39": {"name": "source.my_dbt_project.raw.green_tripdata_2021-04", "type": "source"}, "40": {"name": "source.my_dbt_project.raw.green_tripdata_2021-05", "type": "source"}, "41": {"name": "source.my_dbt_project.raw.green_tripdata_2021-06", "type": "source"}, "42": {"name": "source.my_dbt_project.raw.green_tripdata_2021-07", "type": "source"}, "43": {"name": "source.my_dbt_project.raw.green_tripdata_2021-08", "type": "source"}, "44": {"name": "source.my_dbt_project.raw.green_tripdata_2021-09", "type": "source"}, "45": {"name": "source.my_dbt_project.raw.green_tripdata_2021-10", "type": "source"}, "46": {"name": "source.my_dbt_project.raw.green_tripdata_2021-11", "type": "source"}, "47": {"name": "source.my_dbt_project.raw.green_tripdata_2021-12", "type": "source"}, "48": {"name": "source.my_dbt_project.raw.green_tripdata_2022-01", "type": "source"}, "49": {"name": "source.my_dbt_project.raw.green_tripdata_2022-02", "type": "source"}, "50": {"name": "source.my_dbt_project.raw.green_tripdata_2022-03", "type": "source"}, "51": {"name": "source.my_dbt_project.raw.green_tripdata_2022-04", "type": "source"}, "52": {"name": "source.my_dbt_project.raw.green_tripdata_2022-05", "type": "source"}, "53": {"name": "source.my_dbt_project.raw.green_tripdata_2022-06", "type": "source"}, "54": {"name": "source.my_dbt_project.raw.green_tripdata_2022-07", "type": "source"}, "55": {"name": "source.my_dbt_project.raw.green_tripdata_2022-08", "type": "source", "succ": [121]}, "56": {"name": "source.my_dbt_project.raw.green_tripdata_2022-09", "type": "source"}, "57": {"name": "source.my_dbt_project.raw.green_tripdata_2022-10", "type": "source"}, "58": {"name": "source.my_dbt_project.raw.green_tripdata_2022-11", "type": "source"}, "59": {"name": "source.my_dbt_project.raw.green_tripdata_2022-12", "type": "source"}, "60": {"name": "source.my_dbt_project.raw.green_tripdata_2023-01", "type": "source"}, "61": {"name": "source.my_dbt_project.raw.green_tripdata_2023-02", "type": "source"}, "62": {"name": "source.my_dbt_project.raw.green_tripdata_2023-03", "type": "source"}, "63": {"name": "source.my_dbt_project.raw.green_tripdata_2023-04", "type": "source"}, "64": {"name": "source.my_dbt_project.raw.green_tripdata_2023-05", "type": "source"}, "65": {"name": "source.my_dbt_project.raw.green_tripdata_2023-06", "type": "source"}, "66": {"name": "source.my_dbt_project.raw.green_tripdata_2023-07", "type": "source"}, "67": {"name": "source.my_dbt_project.raw.green_tripdata_2023-08", "type": "source"}, "68": {"name": "source.my_dbt_project.raw.green_tripdata_2023-09", "type": "source"}, "69": {"name": "source.my_dbt_project.raw.green_tripdata_2023-10", "type": "source"}, "70": {"name": "source.my_dbt_project.raw.green_tripdata_2023-11", "type": "source"}, "71": {"name": "source.my_dbt_project.raw.green_tripdata_2023-12", "type": "source"}, "72": {"name": "source.my_dbt_project.raw.green_tripdata_2024-01", "type": "source"}, "73": {"name": "source.my_dbt_project.raw.green_tripdata_2024-02", "type": "source"}, "74": {"name": "source.my_dbt_project.raw.green_tripdata_2024-03", "type": "source"}, "75": {"name": "source.my_dbt_project.raw.green_tripdata_2024-04", "type": "source"}, "76": {"name": "source.my_dbt_project.raw.green_tripdata_2024-05", "type": "source"}, "77": {"name": "source.my_dbt_project.raw.green_tripdata_2024-06", "type": "source"}, "78": {"name": "source.my_dbt_project.raw.green_tripdata_2024-07", "type": "source"}, "79": {"name": "source.my_dbt_project.raw.green_tripdata_2024-08", "type": "source"}, "80": {"name": "source.my_dbt_project.raw.green_tripdata_2024-09", "type": "source"}, "81": {"name": "source.my_dbt_project.raw.green_tripdata_2024-10", "type": "source"}, "82": {"name": "source.my_dbt_project.raw.green_tripdata_2024-11", "type": "source"}, "83": {"name": "source.my_dbt_project.raw.green_tripdata_2024-12", "type": "source"}, "84": {"name": "source.my_dbt_project.raw.green_tripdata_2025-01", "type": "source"}, "85": {"name": "source.my_dbt_project.raw.green_tripdata_2025-02", "type": "source"}, "86": {"name": "source.my_dbt_project.raw.green_tripdata_2025-03", "type": "source"}, "87": {"name": "source.my_dbt_project.raw.green_tripdata_2025-04", "type": "source"}, "88": {"name": "source.my_dbt_project.raw.green_tripdata_2025-05", "type": "source"}, "89": {"name": "source.my_dbt_project.raw.green_tripdata_2025-06", "type": "source"}, "90": {"name": "source.my_dbt_project.raw.green_tripdata_2025-07", "type": "source"}, "91": {"name": "source.my_dbt_project.raw.green_tripdata_2025-08", "type": "source"}, "92": {"name": "source.my_dbt_project.raw.green_tripdata_2025-09", "type": "source"}, "93": {"name": "source.my_dbt_project.raw.green_tripdata_2025-10", "type": "source"}, "94": {"name": "source.my_dbt_project.raw.green_tripdata_2025-11", "type": "source"}, "95": {"name": "source.my_dbt_project.raw.green_tripdata_2025-12", "type": "source"}, "96": {"name": "source.my_dbt_project.raw.green_tripdata_2026-01", "type": "source"}, "97": {"name": "source.my_dbt_project.raw.green_tripdata_2026-02", "type": "source"}, "98": {"name": "source.my_dbt_project.raw.green_tripdata_2026-03", "type": "source"}, "99": {"name": "source.my_dbt_project.raw.green_tripdata_2026-04", "type": "source"}, "100": {"name": "source.my_dbt_project.raw.green_tripdata_2026-05", "type": "source"}, "101": {"name": "source.my_dbt_project.raw.green_tripdata_2026-06", "type": "source"}, "102": {"name": "source.my_dbt_project.raw.green_tripdata_2026-07", "type": "source"}, "103": {"name": "source.my_dbt_project.raw.green_tripdata_2026-08", "type": "source"}, "104": {"name": "source.my_dbt_project.raw.green_tripdata_2026-09", "type": "source"}, "105": {"name": "source.my_dbt_project.raw.green_tripdata_2026-10", "type": "source"}, "106": {"name": "source.my_dbt_project.raw.green_tripdata_2026-11", "type": "source"}, "107": {"name": "source.my_dbt_project.raw.green_tripdata_2026-12", "type": "source"}, "108": {"name": "source.my_dbt_project.raw.green_tripdata_2027-01", "type": "source"}, "109": {"name": "source.my_dbt_project.raw.green_tripdata_2027-02", "type": "source"}, "110": {"name": "source.my_dbt_project.raw.green_tripdata_2027-03", "type": "source"}, "111": {"name": "source.my_dbt_project.raw.green_tripdata_2027-04", "type": "source"}, "112": {"name": "source.my_dbt_project.raw.green_tripdata_2027-05", "type": "source"}, "113": {"name": "source.my_dbt_project.raw.green_tripdata_2027-06", "type": "source"}, "114": {"name": "source.my_dbt_project.raw.green_tripdata_2027-07", "type": "source"}, "115": {"name": "source.my_dbt_project.raw.green_tripdata_2027-08", "type": "source"}, "116": {"name": "source.my_dbt_project.raw.green_tripdata_2027-09", "type": "source"}, "117": {"name": "source.my_dbt_project.raw.green_tripdata_2027-10", "type": "source"}, "118": {"name": "source.my_dbt_project.raw.green_tripdata_2027-11", "type": "source"}, "119": {"name": "source.my_dbt_project.raw.green_tripdata_2027-12", "type": "source"}, "120": {"name": "model.my_dbt_project.marts_green_tripdata_summary_all", "type": "model"}, "121": {"name": "model.my_dbt_project.staging_green_tripdata_current_month", "type": "model", "succ": [120]}, "122": {"name": "test.my_dbt_project.test_calculate_tip_rate", "type": "test"}, "123": {"name": "test.my_dbt_project.test_is_valid_trip", "type": "test"}, "124": {"name": "test.my_dbt_project.test_standardize_payment_type", "type": "test"}, "125": {"name": "seed.my_dbt_project.lookup_data", "type": "seed"}}}